pyliteconf/__init__.py
pyliteconf/config.py
pyliteconf-0.0.4.dist-info/METADATA
pyliteconf-0.0.4.dist-info/WHEEL
pyliteconf-0.0.4.dist-info/top_level.txt
pyliteconf-0.0.4.dist-info/RECORD
