Metadata-Version: 2.1
Name: pyliteconf
Version: 0.0.4
Summary: Library for creating configs on python
Home-page: https://github.com/co-cy/pyliteconf
Author: _co_cy_
Author-email: step2038@mail.ru
License: UNKNOWN
Platform: UNKNOWN
